j1939/__init__.py
j1939/controller_application.py
j1939/diagnostic_messages.py
j1939/electronic_control_unit.py
j1939/j1939_21.py
j1939/j1939_22.py
j1939/memory_access.py
j1939/message_id.py
j1939/name.py
j1939/parameter_group_number.py
j1939/version.py
can_j1939-2.0.12.dist-info/LICENSE
can_j1939-2.0.12.dist-info/METADATA
can_j1939-2.0.12.dist-info/WHEEL
can_j1939-2.0.12.dist-info/top_level.txt
can_j1939-2.0.12.dist-info/RECORD
