Metadata-Version: 2.1
Name: can-j1939
Version: 2.0.12
Summary: SAE J1939 stack implementation
Home-page: https://github.com/juergenH87/python-can-j1939
Author: Juergen Heilgemeir
License: MIT
Keywords: CAN SAE J1939 J1939-FD J1939-22
Platform: any
Classifier: License :: OSI Approved :: MIT License
Classifier: Operating System :: OS Independent
Classifier: Programming Language :: Python :: 3
Classifier: Intended Audience :: Developers
Classifier: Topic :: Scientific/Engineering
License-File: LICENSE
